{"cameraMode":{"drawMode":0,"name":"Shaded","section":"Shading Mode"},"sceneLighting":false,"audioPlay":false,"sceneViewState":{"m_AlwaysRefresh":false,"showFog":true,"showSkybox":false,"showFlares":true,"showImageEffects":true,"showParticleSystems":true,"showVisualEffectGraphs":true,"m_FxEnabled":true},"in2DMode":false,"pivot":{"x":1.5,"y":1.2000000476837159,"z":0.2154960036277771},"rotation":{"x":0.1357555240392685,"y":-0.8458702564239502,"z":0.2563877999782562,"w":0.4478428065776825},"size":2.7646641731262209,"orthographic":false}